{
  "open": [
    {
      "sym": "SHOP",
      "entry": 127.12,
      "amount": 10042.48,
      "shares": 79,
      "date": "2026-07-16",
      "setup": {
        "rev_status": "unknown"
      },
      "off_strategy": "unconfirmed_revenue"
    }
  ],
  "closed": [
    {
      "sym": "DAC",
      "entry": 131.58,
      "amount": 1973.7,
      "shares": 15,
      "date": "2026-06-05",
      "setup": {
        "rev_status": "unknown",
        "note": "Logged manually (chat parser missed the original message). Indicator snapshot not captured at entry."
      },
      "exit": 124.62,
      "pnl_pct": -5.289557683538537,
      "outcome": "loss",
      "pnl_usd": -104.4000000000001,
      "close_date": "2026-06-19"
    },
    {
      "sym": "CWEN",
      "entry": 38.64,
      "amount": null,
      "shares": null,
      "date": "2026-06-19",
      "setup": {
        "rev_status": "unknown"
      },
      "exit": 37.0,
      "pnl_pct": -4.244306418219463,
      "outcome": "loss",
      "pnl_usd": null,
      "close_date": "2026-06-19"
    },
    {
      "sym": "WRBY",
      "entry": 24.06,
      "amount": 1924.8,
      "shares": 80,
      "date": "2026-06-09",
      "setup": {
        "rev_status": "unknown"
      },
      "exit": 25.96,
      "pnl_pct": 7.896924355777232,
      "outcome": "win",
      "pnl_usd": 152.00000000000017,
      "close_date": "2026-06-19"
    },
    {
      "sym": "IRDM",
      "entry": 48.63,
      "amount": null,
      "shares": null,
      "date": "2026-06-19",
      "setup": {
        "rev_status": "unknown"
      },
      "exit": 45.03,
      "pnl_pct": -7.402837754472551,
      "outcome": "loss",
      "pnl_usd": null,
      "close_date": "2026-06-19"
    },
    {
      "sym": "FLEX",
      "entry": 151.0,
      "amount": 4983.0,
      "shares": 33,
      "date": "2026-06-22",
      "setup": {
        "rev_status": "unknown"
      },
      "exit": 145.68,
      "pnl_pct": -3.523178807947015,
      "outcome": "loss",
      "pnl_usd": -175.55999999999977,
      "close_date": "2026-06-23"
    },
    {
      "sym": "FLEX",
      "entry": 151.0,
      "amount": null,
      "shares": null,
      "date": "2026-06-25",
      "setup": {
        "rev_status": "unknown"
      },
      "exit": 145.68,
      "pnl_pct": -3.523178807947015,
      "outcome": "loss",
      "pnl_usd": null,
      "close_date": "2026-06-25"
    },
    {
      "sym": "FCFS",
      "entry": 225.59,
      "amount": 4962.98,
      "shares": 22,
      "date": "2026-06-12",
      "setup": {
        "rev_status": "unknown"
      },
      "exit": 214.71,
      "pnl_pct": -4.822908816880179,
      "outcome": "loss",
      "pnl_usd": -239.35999999999984,
      "close_date": "2026-06-26"
    },
    {
      "sym": "KWR",
      "entry": 151.22,
      "amount": 4990.26,
      "shares": 33,
      "date": "2026-06-19",
      "setup": {
        "rev_status": "unknown"
      },
      "exit": 155.5,
      "pnl_pct": 2.830313450601773,
      "outcome": "win",
      "pnl_usd": 141.24000000000007,
      "close_date": "2026-06-29"
    },
    {
      "sym": "TCBK",
      "entry": 50.84,
      "amount": 2033.6,
      "shares": 40,
      "date": "2026-06-05",
      "setup": {
        "rev_status": "unknown",
        "sector": "regional banks",
        "note": "Logged manually (chat parser missed the original message). Indicator snapshot not captured at entry."
      },
      "exit": 52.68,
      "pnl_pct": 3.619197482297396,
      "outcome": "win",
      "pnl_usd": 73.59999999999985,
      "close_date": "2026-07-08"
    },
    {
      "sym": "JNJ",
      "entry": 253.47,
      "amount": 5069.4,
      "shares": 20,
      "date": "2026-07-01",
      "setup": {
        "rev_status": "unknown"
      },
      "exit": 248.29,
      "pnl_pct": -2.0436343551505134,
      "outcome": "loss",
      "pnl_usd": -103.60000000000012,
      "close_date": "2026-07-15"
    },
    {
      "sym": "ARGX",
      "entry": 950.38,
      "amount": 251850.7,
      "shares": 265,
      "date": "2026-07-03",
      "setup": {
        "rev_status": "unknown"
      },
      "off_strategy": "unconfirmed_revenue",
      "exit": 880.26,
      "pnl_pct": -7.378101391022539,
      "outcome": "loss",
      "pnl_usd": -18581.800000000003,
      "close_date": "2026-07-15"
    },
    {
      "sym": "HOOD",
      "entry": 100.1,
      "amount": 3003.0,
      "shares": 30,
      "date": "2026-06-29",
      "setup": {
        "rev_status": "unknown"
      },
      "exit": 108.61,
      "pnl_pct": 8.501498501498506,
      "outcome": "win",
      "pnl_usd": 255.30000000000015,
      "close_date": "2026-07-16"
    },
    {
      "sym": "CNS",
      "entry": 77.55,
      "amount": 2016.3,
      "shares": 26,
      "date": "2026-06-26",
      "setup": {
        "rev_status": "unknown"
      },
      "exit": 74.35,
      "pnl_pct": -4.126370083816896,
      "outcome": "loss",
      "pnl_usd": -83.20000000000007,
      "close_date": "2026-07-17"
    }
  ],
  "watch": [
    "CLBT",
    "NBIS",
    "RDDT",
    "SHOP",
    "LII",
    "MAS",
    "CART",
    "HEI"
  ],
  "account": {
    "starting_capital": 100000
  },
  "watch_targets": {
    "SHOP": 139.5
  }
}